{
  "project_info": {
    "project_number": "854540743036",
    "project_id": "zakat-4ab66",
    "storage_bucket": "zakat-4ab66.appspot.com"
  },
  "client": [
    {
      "client_info": {
        "mobilesdk_app_id": "1:854540743036:android:d17e28e8e917c2585cb4f9",
        "android_client_info": {
          "package_name": "com.example.untitled"
        }
      },
      "oauth_client": [],
      "api_key": [
        {
          "current_key": "AIzaSyBhu6K_mXNFFMEB1Qgoze5FDP_DR90ifOc"
        }
      ],
      "services": {
        "appinvite_service": {
          "other_platform_oauth_client": []
        }
      }
    }
  ],
  "configuration_version": "1"
}